{"title":"Myyrän aarre","id":"kavi.elonet_elokuva_1028288","images":["/Cover/Show?id=kavi.elonet_elokuva_1028288&index=0&size=large&source=Solr","/Cover/Show?id=kavi.elonet_elokuva_1028288&index=1&size=large&source=Solr","/Cover/Show?id=kavi.elonet_elokuva_1028288&index=2&size=large&source=Solr","/Cover/Show?id=kavi.elonet_elokuva_1028288&index=3&size=large&source=Solr","/Cover/Show?id=kavi.elonet_elokuva_1028288&index=4&size=large&source=Solr","/Cover/Show?id=kavi.elonet_elokuva_1028288&index=5&size=large&source=Solr","/Cover/Show?id=kavi.elonet_elokuva_1028288&index=6&size=large&source=Solr","/Cover/Show?id=kavi.elonet_elokuva_1028288&index=7&size=large&source=Solr","/Cover/Show?id=kavi.elonet_elokuva_1028288&index=8&size=large&source=Solr","/Cover/Show?id=kavi.elonet_elokuva_1028288&index=9&size=large&source=Solr","/Cover/Show?id=kavi.elonet_elokuva_1028288&index=10&size=large&source=Solr","/Cover/Show?id=kavi.elonet_elokuva_1028288&index=11&size=large&source=Solr","/Cover/Show?id=kavi.elonet_elokuva_1028288&index=12&size=large&source=Solr","/Cover/Show?id=kavi.elonet_elokuva_1028288&index=13&size=large&source=Solr","/Cover/Show?id=kavi.elonet_elokuva_1028288&index=14&size=large&source=Solr","/Cover/Show?id=kavi.elonet_elokuva_1028288&index=15&size=large&source=Solr","/Cover/Show?id=kavi.elonet_elokuva_1028288&index=16&size=large&source=Solr","/Cover/Show?id=kavi.elonet_elokuva_1028288&index=17&size=large&source=Solr","/Cover/Show?id=kavi.elonet_elokuva_1028288&index=18&size=large&source=Solr","/Cover/Show?id=kavi.elonet_elokuva_1028288&index=19&size=large&source=Solr","/Cover/Show?id=kavi.elonet_elokuva_1028288&index=20&size=large&source=Solr","/Cover/Show?id=kavi.elonet_elokuva_1028288&index=21&size=large&source=Solr"],"urls":[{"url":"https://vimeo.com/420615723","text":"elokuva","desc":"elokuva","source":"kavi","embed":"iframe","warnings":["age_rating_for_all_ages"]}],"recordPage":"/Record/kavi.elonet_elokuva_1028288","imageRights":{"copyright":"Luvanvarainen käyttö / ei tiedossa"},"buildings":[{"value":"0/KAVI/","translated":"Kansallinen audiovisuaalinen instituutti"}],"rawData":{"record_format":"forward","ctrlnum":["elonet_elokuva_1028288"],"title":"Myyrän aarre","title_txtP":"Myyrän aarre","title_alt":["Mole's Treasure","Mullvadens skatt"],"title_full":"Myyrän aarre","title_fullStr":"Myyrän aarre","title_full_unstemmed":"Myyrän aarre","title_short":"Myyrän aarre","description":"Pieni myyrä etsii pudonnutta tähteä öisestä metsästä, jossa kaikki muut jo näyttävät löytäneen aarteensa.","topic":["itsekkyys"],"url":["http://www.elonet.fi/fi/elokuva/1028288","http://www.elonet.fi/fi/video/1685347_1028288"],"thumbnail":"http://www.elonet.fi/tenho/media/164828_V1108126E0.jpg","author":["Tini Sauvo"],"author_role":["d02"],"author_sort":"Tini Sauvo","author2":["Tini Sauvo","Tero Makkonen","Tuuli Kuittinen","Vesa Mäkelä"],"author2_role":["aus","cng","flm","anm","e01"],"author_corporate":["Liisa Helminen Film Productions Oy","AVEK","Suomen elokuvasäätiö SES"],"author_corporate_role":["e10","fnd"],"geographic":["Suomi"],"genre":["lastenelokuva","animaatio"],"format":[{"value":"0/Video/","translated":"Video"},{"value":"1/Video/Short/","translated":"Elokuva, lyhyt"}],"main_date":"2001-01-01T00:00:00Z","publication_daterange":"[2001-01-01 TO 2001-12-31]","search_daterange_mv":["[2001-01-01 TO 2001-12-31]"],"author_facet":["Tini Sauvo","Tero Makkonen","Tuuli Kuittinen","Vesa Mäkelä","Liisa Helminen Film Productions Oy","AVEK","Suomen elokuvasäätiö SES"],"language":["fin"],"id":"kavi.elonet_elokuva_1028288","is_hierarchy_id":"kavi.elonet_elokuva_1028288","is_hierarchy_title":"Myyrän aarre","first_indexed":"2017-04-11T11:50:41Z","last_indexed":"2021-04-30T06:32:05Z","publishDate":["2001"],"subtitle_lng_str_mv":["eng"],"building":[{"value":"0/KAVI/","translated":"Kansallinen audiovisuaalinen instituutti"}],"institution":["KAVI"],"sector_str_mv":[{"value":"0/arc/","translated":"Arkisto"}],"topic_facet":["itsekkyys"],"online_boolean":1,"genre_facet":["animaatio","lastenelokuva"],"online_str_mv":["kavi"],"free_online_str_mv":["kavi"],"source_str_mv":["kavi"],"work_keys_str_mv":["AT sauvotini myyränaarre"],"geographic_facet":["Suomi"],"author2_id_str_mv":["kavi.elonet_henkilo_100968","kavi.elonet_henkilo_105283","kavi.elonet_henkilo_116540","kavi.elonet_henkilo_116743","kavi.elonet_henkilo_131144","kavi.elonet_henkilo_161704","kavi.elonet_yhtio_216015","kavi.elonet_yhtio_710032","kavi.elonet_yhtio_710034","kavi.elonet_yhtio_714900"],"author2_id_role_str_mv":["kavi.elonet_henkilo_100968###flm","kavi.elonet_henkilo_105283###act","kavi.elonet_henkilo_116540###anm","kavi.elonet_henkilo_116540###aus","kavi.elonet_henkilo_116540###drt","kavi.elonet_henkilo_116743###musiikki","kavi.elonet_henkilo_131144###rce","kavi.elonet_henkilo_161704###cng","kavi.elonet_yhtio_216015###fmp","kavi.elonet_yhtio_710032###fnd","kavi.elonet_yhtio_710034###fnd","kavi.elonet_yhtio_714900###fds"],"main_date_str":"2001","title_sort":"Myyrän aarre","free_online_boolean":1,"online_urls_str_mv":["{\"url\":\"http:\\/\\/www.elonet.fi\\/fi\\/video\\/1685347_1028288\",\"text\":\"elokuva\",\"source\":\"kavi\"}"],"format_ext_str_mv":[{"value":"0/Image/","translated":"Kuva"},{"value":"0/Video/","translated":"Video"},{"value":"1/Image/Image/","translated":"Kuva"},{"value":"1/Video/Short/","translated":"Elokuva, lyhyt"}],"datasource_str_mv":["kavi"],"_version_":1704698154693165000}}