{"title":"Alkoholi ja työyhteisö","id":"kavi.elonet_elokuva_169460","images":["/Cover/Show?id=kavi.elonet_elokuva_169460&index=0&size=large&source=Solr"],"urls":[{"url":"http://www.elonet.fi/fi/video/1392153_169460","posterUrl":"http://www.elonet.fi/tenho/media/1392153_suoratoisto_esikatselu.jpg","videoSources":[{"src":"https://elo.salama.tv.funet.fi/vod/_definst_/mp4:fi/kava/elonet/2015/TUV-610_AlkoholiJaTyoyhteiso.mp4/playlist.m3u8","type":"application/x-mpegURL","priority":1},{"src":"https://elo.salama.tv.funet.fi/vod/_definst_/mp4:fi/kava/elonet/2015/TUV-610_AlkoholiJaTyoyhteiso.mp4/manifest.mpd","type":"application/dash+xml","priority":2}],"text":"elokuva","desc":"elokuva","source":"kavi","embed":"video","warnings":["age_rating_for_all_ages"]}],"recordPage":"/Record/kavi.elonet_elokuva_169460","imageRights":{"copyright":"Luvanvarainen käyttö / ei tiedossa"},"buildings":[{"value":"0/KAVI/","translated":"Kansallinen audiovisuaalinen instituutti"}],"rawData":{"record_format":"forward","ctrlnum":["elonet_elokuva_169460"],"title":"Alkoholi ja työyhteisö","title_txtP":"Alkoholi ja työyhteisö","title_full":"Alkoholi ja työyhteisö","title_fullStr":"Alkoholi ja työyhteisö","title_full_unstemmed":"Alkoholi ja työyhteisö","title_short":"Alkoholi ja työyhteisö","description":"Työelämän alkoholiongelmia, niiden syntyä ja taustaa sekä ongelmaisten hoitoonohjausta, sen tavoitteita, sisältöä ja menetelmiä sekä hoitoa käsittelevä elokuva.","topic":["alkoholiongelmat","työelämä","hoito"],"url":["http://www.elonet.fi/fi/elokuva/169460","http://www.elonet.fi/fi/video/1392153_169460"],"thumbnail":"http://www.elonet.fi/tenho/media/1392153_digikuva_suoratoisto_thumbnail.jpg","author":["Jaakko Pakkasvirta"],"author_role":["d02"],"author_sort":"Jaakko Pakkasvirta","author2":["Jaakko Pakkasvirta","Esa Vuorinen","Ari Mäkinen","Heimo Hämäläinen","Kari Roos","Kari Ingelin","Erkki J. Anttila","Seija Lenkkeri"],"author2_role":["aus","cng","flm","e01"],"author_corporate":["Filmityö Oy"],"author_corporate_role":["e10"],"geographic":["Suomi"],"genre":["opetuselokuva","valistuselokuva","dokumentti"],"format":[{"value":"0/Video/","translated":"Video"},{"value":"1/Video/Short/","translated":"Elokuva, lyhyt"}],"main_date":"1979-01-01T00:00:00Z","publication_daterange":"[1979-01-01 TO 1979-12-31]","search_daterange_mv":["[1979-01-01 TO 1979-12-31]"],"author_facet":["Jaakko Pakkasvirta","Esa Vuorinen","Ari Mäkinen","Heimo Hämäläinen","Kari Roos","Kari Ingelin","Erkki J. Anttila","Seija Lenkkeri","Filmityö Oy"],"language":["fin"],"id":"kavi.elonet_elokuva_169460","is_hierarchy_id":"kavi.elonet_elokuva_169460","is_hierarchy_title":"Alkoholi ja työyhteisö","first_indexed":"2017-04-11T11:52:46Z","last_indexed":"2021-04-30T06:33:53Z","publishDate":["1979"],"building":[{"value":"0/KAVI/","translated":"Kansallinen audiovisuaalinen instituutti"}],"institution":["KAVI"],"sector_str_mv":[{"value":"0/arc/","translated":"Arkisto"}],"topic_facet":["alkoholiongelmat","hoito","työelämä"],"online_boolean":1,"genre_facet":["dokumentti","opetuselokuva","valistuselokuva"],"online_str_mv":["kavi"],"free_online_str_mv":["kavi"],"source_str_mv":["kavi"],"work_keys_str_mv":["AT pakkasvirtajaakko alkoholijatyöyhteisö"],"geographic_facet":["Suomi"],"author2_id_str_mv":["kavi.elonet_henkilo_100066","kavi.elonet_henkilo_100067","kavi.elonet_henkilo_100165","kavi.elonet_henkilo_100550","kavi.elonet_henkilo_101031","kavi.elonet_henkilo_1010532","kavi.elonet_henkilo_1010533","kavi.elonet_henkilo_1010534","kavi.elonet_henkilo_1010535","kavi.elonet_henkilo_1393430","kavi.elonet_henkilo_234158","kavi.elonet_henkilo_236886","kavi.elonet_henkilo_873135","kavi.elonet_yhtio_107308","kavi.elonet_yhtio_209409","kavi.elonet_yhtio_222159","kavi.elonet_yhtio_222885","kavi.elonet_yhtio_492172","kavi.elonet_yhtio_717348"],"author2_id_role_str_mv":["kavi.elonet_henkilo_100066###cng","kavi.elonet_henkilo_100067###rce","kavi.elonet_henkilo_100165###työryhmä","kavi.elonet_henkilo_100550###aus","kavi.elonet_henkilo_100550###drt","kavi.elonet_henkilo_100550###flm","kavi.elonet_henkilo_101031###työryhmä","kavi.elonet_henkilo_1010532###act","kavi.elonet_henkilo_1010533###act","kavi.elonet_henkilo_1010534###act","kavi.elonet_henkilo_1010535###act","kavi.elonet_henkilo_1393430###suunnittelutyöryhmän pj\\.","kavi.elonet_henkilo_234158###act","kavi.elonet_henkilo_236886###act","kavi.elonet_henkilo_873135###työryhmä","kavi.elonet_yhtio_107308###tilaaja","kavi.elonet_yhtio_209409###fmp","kavi.elonet_yhtio_222159###fds","kavi.elonet_yhtio_222885###fds","kavi.elonet_yhtio_492172###fds","kavi.elonet_yhtio_717348###fds"],"main_date_str":"1979","title_sort":"Alkoholi ja työyhteisö","free_online_boolean":1,"online_urls_str_mv":["{\"url\":\"http:\\/\\/www.elonet.fi\\/fi\\/video\\/1392153_169460\",\"text\":\"elokuva\",\"source\":\"kavi\"}"],"format_ext_str_mv":[{"value":"0/Image/","translated":"Kuva"},{"value":"0/Video/","translated":"Video"},{"value":"1/Image/Image/","translated":"Kuva"},{"value":"1/Video/Short/","translated":"Elokuva, lyhyt"}],"datasource_str_mv":["kavi"],"_version_":1704525847488102400}}