{"title":"Maaseudun antimet","id":"kavi.elonet_elokuva_107632","images":["/Cover/Show?id=kavi.elonet_elokuva_107632&index=0&size=large&source=Solr"],"urls":[{"url":"http://www.elonet.fi/fi/video/1652173_107632","posterUrl":"http://www.elonet.fi/tenho/media/1652173_suoratoisto_esikatselu.jpg","videoSources":[{"src":"https://elo.salama.tv.funet.fi/vod/_definst_/mp4:fi/kava/elonet/2012/900358_MaaseudunAntimet.mp4/playlist.m3u8","type":"application/x-mpegURL","priority":1},{"src":"https://elo.salama.tv.funet.fi/vod/_definst_/mp4:fi/kava/elonet/2012/900358_MaaseudunAntimet.mp4/manifest.mpd","type":"application/dash+xml","priority":2}],"text":"elokuva","desc":"elokuva","source":"kavi","embed":"video","warnings":[]}],"recordPage":"/Record/kavi.elonet_elokuva_107632","imageRights":{"copyright":"Luvanvarainen käyttö / ei tiedossa"},"buildings":[{"value":"0/KAVI/","translated":"Kansallinen audiovisuaalinen instituutti"}],"rawData":{"record_format":"forward","ctrlnum":["elonet_elokuva_107632"],"title":"Maaseudun antimet","title_txtP":"Maaseudun antimet","title_full":"Maaseudun antimet","title_fullStr":"Maaseudun antimet","title_full_unstemmed":"Maaseudun antimet","title_short":"Maaseudun antimet","description":"Elokuvassa esitellään SOK:n jakelujärjestelmää. Alkutekstit, taustalla maalaismaisemaa. Sumu nousee pellolta. Peltomaisemaa, karjaa. Lukija puhuu maataloudesta Suomen pääelinkeinona, kehuu karjatalouden kannattavuutta ja sen tuotteiden tehokasta markkinointia.<br /><br />Meijerin pihalla. Lukija kertoo maanviljelijöiden luoneen koko maan kattavan osuusmeijeriverkoston. Hinkkejä nostetaan liukuhihnalle, sisällä meijerissä valkopukuinen nainen tyhjentää ne.<br />Lukija: Jonka koneistoissa maito jalostetaan ennen kaikkea korkealla tasolla, että esimerkiksi suomalainen juusto tunnetaan erinomaiseksi Afrikassa saakka. Samoin voimme voittaa voilla vaikkapa ensipalkintoja.<br /><br />Maalaismaisemaa, heinää seipäillä. Viljan puintia, torilla käydään kauppaa. Kuvia SOK:n viljasiilosta. Laboratoriossa tutkitaan viljan laatua. Lukija selittää viljan hinnoittelun perusteita. Kuvia myllystä ja leipomosta. Valkopukuiset naiset leipovat, taustalla soi \"niin kauas kuin silmäin siintää\" (Kesäpäivä Kangasalla).<br /> <br />Miehet kantavat sikaa kuorma-auton lavalle. Lukija puhuu teurastuksesta. Auton lava tupaten täynnä sikoja. Kanatarha, nainen tuo munakorillisen kauppaan. Lukija selittää, että varastoinnin avulla voidaan suhdanneherkkää munatuotantoa jonkun verran tasoittaa. Naiset töissä munapakkaamossa.<br />Omenia poimitaan.<br />Lukija: Huolimatta ankarista sääolosuhteista on näiden ihmisten hyvinvoinnille tärkeiden elintarvikkeiden tuotanto edistynyt, erikoisesti siinä suhteessa, että kuluttajille on viime aikoina pystytty tarjoamaan entistä parempilaatuisia tuotteita.<br />Mies poimii kurkkuja kasvihuoneessa. Kurkut viedään autolla osuuskauppaan. Nainen lajittelee avomaan kurkkuja suolakurkkujen raaka-aineeksi.<br /><br />Perunan nostoa. Lukija suosittelee käsinnostoa, jos halutaan hyvää ruokaperunaa. Naiset lajittelevat ja pakkaavat tehtaassa perunoita.<br />Lukija: Hyvää tavaraa vaativien asiakkaiden lisääntyessä on alettu viljellä ja toimittaa kauppaan erityistä herkkuperunaa, jonka tuottamista, lajittelua ja pakkaamista valvotaan valtiovallan toimesta. <br />Kalaa satamassa. Lukija kertoo tuoreen kalan välittämisen vaikeudesta. Marjanpoimintaa, marjoja kaupassa. Satamassa marjoja menossa vientiin.<br /><br />Kauppakuvia.<br />Lukija: Tuotteiden kaupassa on kaksi puolta: keräily ja vähittäismyynti. ..Tuotteet ostetaan ylituotantoseutujen myymälöissä. Kun tuote-erä on sääntöjen mukaisesti lajiteltu ja pakattu, se toimitetaan suorinta tietä kulutusseudulle, jossa myyntiä hoitavat nykyaikaisesti sisustetut ruokatavaramyymälät.<br /><br />Viljelijä osuuskaupan johtajan luona. Viljelijä menee nostamaan säästökassasta rahaa myymistään tuotteista. <br />Lukija: Omakohtainen asioiminen kauppaliikkeessä ohjaa meidät taloudellisen ajattelun tielle muistuttaen samalla siitä tosiasiasta, että vain säästeliäällä elämäntavalla luodaan perusta yksilön, perheen ja koko kansan onnelliselle tulevaisuudelle. Yhdistämällä saman järjestön piiriin maaseudun  antimien keräilyn ja kaupan sekä kulutustavaroiden myynnin palvellaan kansantaloutta parhaalla mahdollisella tavalla.<br />Kauppakuvia ulkoa.","topic":["maatalous","maanviljely","kotieläintalous","elintarviketuotanto","elintarvikkeet","myymälät","satamat","jakelu","meijerit","vähittäiskauppa"],"url":["http://www.elonet.fi/fi/elokuva/107632","http://www.elonet.fi/fi/video/1652173_107632"],"thumbnail":"http://www.elonet.fi/tenho/media/1652173_digikuva_suoratoisto_thumbnail.jpg","author":["Pentti Massinen"],"author_role":["d02"],"author_sort":"Pentti Massinen","author2":["Pentti Massinen","Yrjö Aaltonen"],"author2_role":["aus","cng"],"author_corporate":["Suomi-Filmi Oy"],"author_corporate_role":["e10"],"geographic":["Suomi"],"genre":["tilauselokuva","esittelyelokuva","maatalousdokumentti","dokumentti"],"format":[{"value":"0/Video/","translated":"Video"},{"value":"1/Video/Short/","translated":"Elokuva, lyhyt"}],"main_date":"1952-01-01T00:00:00Z","publication_daterange":"[1952-01-01 TO 1952-12-31]","search_daterange_mv":["[1952-01-01 TO 1952-12-31]"],"author_facet":["Pentti Massinen","Yrjö Aaltonen","Suomi-Filmi Oy"],"language":["fin"],"id":"kavi.elonet_elokuva_107632","is_hierarchy_id":"kavi.elonet_elokuva_107632","is_hierarchy_title":"Maaseudun antimet","first_indexed":"2017-04-11T11:51:44Z","last_indexed":"2021-04-30T06:33:00Z","publishDate":["1952"],"building":[{"value":"0/KAVI/","translated":"Kansallinen audiovisuaalinen instituutti"}],"institution":["KAVI"],"sector_str_mv":[{"value":"0/arc/","translated":"Arkisto"}],"topic_facet":["elintarviketuotanto","elintarvikkeet","jakelu","kotieläintalous","maanviljely","maatalous","meijerit","myymälät","satamat","vähittäiskauppa"],"online_boolean":1,"genre_facet":["dokumentti","esittelyelokuva","maatalousdokumentti","tilauselokuva"],"online_str_mv":["kavi"],"free_online_str_mv":["kavi"],"source_str_mv":["kavi"],"work_keys_str_mv":["AT massinenpentti maaseudunantimet"],"geographic_facet":["Suomi"],"author2_id_str_mv":["kavi.elonet_henkilo_100046","kavi.elonet_henkilo_102478","kavi.elonet_henkilo_738813","kavi.elonet_yhtio_102797","kavi.elonet_yhtio_111432"],"author2_id_role_str_mv":["kavi.elonet_henkilo_100046###spk,","kavi.elonet_henkilo_102478###cng","kavi.elonet_henkilo_738813###aus","kavi.elonet_henkilo_738813###drt","kavi.elonet_yhtio_102797###tilaaja","kavi.elonet_yhtio_111432###fmp"],"main_date_str":"1952","title_sort":"Maaseudun antimet","free_online_boolean":1,"online_urls_str_mv":["{\"url\":\"http:\\/\\/www.elonet.fi\\/fi\\/video\\/1652173_107632\",\"text\":\"elokuva\",\"source\":\"kavi\"}"],"format_ext_str_mv":[{"value":"0/Image/","translated":"Kuva"},{"value":"0/Video/","translated":"Video"},{"value":"1/Image/Image/","translated":"Kuva"},{"value":"1/Video/Short/","translated":"Elokuva, lyhyt"}],"datasource_str_mv":["kavi"],"_version_":1704698157909147600}}