{"title":"Filmiviikko","id":"kavi.elonet_elokuva_157008","images":["/Cover/Show?id=kavi.elonet_elokuva_157008&index=0&size=large&source=Solr"],"urls":[{"url":"http://www.elonet.fi/fi/video/1651644_157008","posterUrl":"http://www.elonet.fi/tenho/media/1651644_suoratoisto_esikatselu.jpg","videoSources":[{"src":"https://elo.salama.tv.funet.fi/vod/_definst_/mp4:fi/kava/elonet/2012/MV-200_Filmiviikko.mp4/playlist.m3u8","type":"application/x-mpegURL","priority":1},{"src":"https://elo.salama.tv.funet.fi/vod/_definst_/mp4:fi/kava/elonet/2012/MV-200_Filmiviikko.mp4/manifest.mpd","type":"application/dash+xml","priority":2}],"text":"elokuva","desc":"elokuva","source":"kavi","embed":"video","warnings":[]}],"recordPage":"/Record/kavi.elonet_elokuva_157008","imageRights":{"copyright":"Luvanvarainen käyttö / ei tiedossa"},"genres":["ajankohtaisdokumentti","dokumentti"],"summary":["\"Kuvanälkä\" oli sodanjälkeisinä vuosina valtava. Suomen elokuva-ala yhdisti voimansa syksyllä 1949 ja toteutti ensimmäisen suomalaisen filmiviikon sekä suurissa kaupungeissa että pienemmillä paikkakunnilla. Viikon aikana nähtiin 20 ensi-iltaa. Elokuvaväen ja elokuvayleisön vuorovaikutus korostui monin tempauksin. Juhlalliset avajaiset pidettiin Helsingin Kino-Palatsissa. Vuonna 1949 Suomessa oli 470 elokuvateatteria ja 40 elokuvavuokraamoa. Tuona vuonna suomalaiset kävivät elokuvissa 26 miljoonaa kertaa."],"buildings":[{"value":"0/KAVI/","translated":"Kansallinen audiovisuaalinen instituutti"}]}