{"title":"Helsingin Sanomat","id":"kavi.elonet_elokuva_161087","images":["/Cover/Show?id=kavi.elonet_elokuva_161087&index=0&size=large&source=Solr"],"urls":[{"url":"http://www.elonet.fi/fi/video/877636_161087","posterUrl":"http://www.elonet.fi/tenho/media/877636_suoratoisto_esikatselu.jpg","videoSources":[{"src":"https://elo.salama.tv.funet.fi/vod/_definst_/mp4:fi/kava/elonet/2013/877636_HelsinginSanomat.mp4/playlist.m3u8","type":"application/x-mpegURL","priority":1},{"src":"https://elo.salama.tv.funet.fi/vod/_definst_/mp4:fi/kava/elonet/2013/877636_HelsinginSanomat.mp4/manifest.mpd","type":"application/dash+xml","priority":2}],"text":"elokuva","desc":"elokuva","source":"kavi","embed":"video","warnings":["age_rating_for_all_ages"]}],"recordPage":"/Record/kavi.elonet_elokuva_161087","imageRights":{"copyright":"Luvanvarainen käyttö / ei tiedossa"},"genres":["esittelyelokuva","dokumentti"],"summary":["Elokuva esittelee, miten Helsingin Sanomat syntyy."],"buildings":[{"value":"0/KAVI/","translated":"Kansallinen audiovisuaalinen instituutti"}]}