{"title":"Lauri Kr. Relander 1925-1931","id":"kavi.elonet_elokuva_133454","images":["/Cover/Show?id=kavi.elonet_elokuva_133454&index=0&size=large&source=Solr"],"urls":[{"url":"http://www.elonet.fi/fi/video/928443_133454","posterUrl":"http://www.elonet.fi/tenho/media/928443_suoratoisto_esikatselu.jpg","videoSources":[{"src":"https://elo.salama.tv.funet.fi/vod/_definst_/mp4:fi/kava/elonet/2012/928443_LauriKRRelander19251931.mp4/playlist.m3u8","type":"application/x-mpegURL","priority":1},{"src":"https://elo.salama.tv.funet.fi/vod/_definst_/mp4:fi/kava/elonet/2012/928443_LauriKRRelander19251931.mp4/manifest.mpd","type":"application/dash+xml","priority":2}],"text":"elokuva","desc":"elokuva","source":"kavi","embed":"video","warnings":[]}],"recordPage":"/Record/kavi.elonet_elokuva_133454","imageRights":{"copyright":"Luvanvarainen käyttö / ei tiedossa"},"buildings":[{"value":"0/KAVI/","translated":"Kansallinen audiovisuaalinen instituutti"}],"rawData":{"record_format":"forward","ctrlnum":["elonet_elokuva_133454"],"title":"Lauri Kr. Relander 1925-1931","title_txtP":"Lauri Kr. Relander 1925-1931","title_alt":["Lauri Kristian Relander","Lauri Kr. Relander","Presidentti Lauri Kr. Relander"],"title_full":"Lauri Kr. Relander 1925-1931","title_fullStr":"Lauri Kr. Relander 1925-1931","title_full_unstemmed":"Lauri Kr. Relander 1925-1931","title_short":"Lauri Kr. Relander 1925-1931","description":"Presidentti Lauri Relanderin matkoja ja vieraita. Elokuva sisältää jaksoja viidestä vuosina 1925-1928 kuvatusta mykkäelokuvasta. Presidentti Relander matkustaa veneessä kohti Tallinnaa. Nousee veneestä ja tarkastaa kunniakomppanian. Seuraa sotilasparaatia (jakso elokuvasta Presidentin vierailu ja loistava vastaanotto Virossa 1925/Suomen presidentin Lauri Relanderin vierailu Virossa 1925 - tekninen kortti). Ruotsin kuningas vastaanottaa Relanderin Tukholmassa kesäkuussa 1925. Kävelevät satamassa. Saapuvat linnaan hevoskyydillä (jakso elokuvasta Suomen Presidentin Lauri Relanderin vierailu Tukholmaan v. 1925/Suomen Presidentin Lauri Relanderin matka Tukholmaan 1925 - tekninen kortti). Relander ottaa vastaan Latvian presidentin Eteläsatamassa vuonna 1926. Tekevät kiertoajelun ja ottavat vastaan paraatin Senaatintorilla (Latvian presidentin vierailu Helsingissä/Latvian presidentti Helsingissä - tekninen kortti, Latvian presidentin vierailu H:gissä - elokuvatarkastamo). Tanskan kuningas Kristian X saapuu Suomenlinnan kautta Eteläsatamaan (Tanskan kuningas Helsingissä/Tanskan kuningas Suomessa - tekninen kortti, Tanskan kuninkaan vierailu/Tanskan kuninkaan vierailu Helsingissä - elokuvatarkastamo). Presidenttipari saapuu junalla Imatralle. Relander vihkii voimalaitoksen. Norjan kuningas Haakon VII:n vierailun vastaanottoseremoniat (Norjan kuningas Haakon VII Suomessa/H.M. Norjan kuninkaan Haakon VII vierailu Suomessa - tekninen kortti, Norjan kuningasvierailu Helsingissä/Norjan kuninkaan vierailu - elokuvatarkastamo). Sotilaat vastaanottavat presidenttiparin Hämeenlinnan rautatieasemalla.","topic":["presidentit","Relander, Lauri Kristian","Tallinna","Kristian X, Tanskan kuningas","Haakon VII, Norjan kuningas","Viro","1925","Tukholma","Latvia","1926","rautatieasemat","Hämeenlinna","Helsinki","Senaatintori","Suomenlinna","Eteläsatama"],"url":["http://www.elonet.fi/fi/elokuva/133454","http://www.elonet.fi/fi/video/928443_133454"],"thumbnail":"http://www.elonet.fi/tenho/media/928443_digikuva_suoratoisto_thumbnail.jpg","author_corporate":["Suomi-Filmi Oy"],"author_corporate_role":["e10"],"geographic":["Suomi"],"genre":["henkilödokumentti","historiallinen dokumentti","dokumentti"],"format":[{"value":"0/Video/","translated":"Video"},{"value":"1/Video/Short/","translated":"Elokuva, lyhyt"}],"main_date":"1957-01-01T00:00:00Z","publication_daterange":"[1957-01-01 TO 1957-12-31]","search_daterange_mv":["[1957-01-01 TO 1957-12-31]"],"author_facet":["Suomi-Filmi Oy"],"language":["fin"],"id":"kavi.elonet_elokuva_133454","is_hierarchy_id":"kavi.elonet_elokuva_133454","is_hierarchy_title":"Lauri Kr. Relander 1925-1931","first_indexed":"2017-04-11T11:49:53Z","last_indexed":"2021-04-30T06:31:28Z","publishDate":["1957"],"building":[{"value":"0/KAVI/","translated":"Kansallinen audiovisuaalinen instituutti"}],"institution":["KAVI"],"sector_str_mv":[{"value":"0/arc/","translated":"Arkisto"}],"topic_facet":["1925","1926","Eteläsatama","Haakon VII, Norjan kuningas","Helsinki","Hämeenlinna","Kristian X, Tanskan kuningas","Latvia","Relander, Lauri Kristian","Senaatintori","Suomenlinna","Tallinna","Tukholma","Viro","presidentit","rautatieasemat"],"online_boolean":1,"genre_facet":["dokumentti","henkilödokumentti","historiallinen dokumentti"],"online_str_mv":["kavi"],"free_online_str_mv":["kavi"],"source_str_mv":["kavi"],"geographic_facet":["Suomi"],"author2_id_str_mv":["kavi.elonet_henkilo_100046","kavi.elonet_henkilo_101559","kavi.elonet_henkilo_1329868","kavi.elonet_yhtio_111432"],"author2_id_role_str_mv":["kavi.elonet_henkilo_100046###Selostaja","kavi.elonet_henkilo_101559###Selostus","kavi.elonet_henkilo_1329868###dokumentti-esiintyjä","kavi.elonet_yhtio_111432###fmp"],"main_date_str":"1957","title_sort":"Lauri Kr. Relander 1925-1931","free_online_boolean":1,"online_urls_str_mv":["{\"url\":\"http:\\/\\/www.elonet.fi\\/fi\\/video\\/928443_133454\",\"text\":\"elokuva\",\"source\":\"kavi\"}"],"format_ext_str_mv":[{"value":"0/Image/","translated":"Kuva"},{"value":"0/Video/","translated":"Video"},{"value":"1/Image/Image/","translated":"Kuva"},{"value":"1/Video/Short/","translated":"Elokuva, lyhyt"}],"datasource_str_mv":["kavi"],"_version_":1704525812088176600}}