{"title":"Mielihyvä 15 sek.","id":"kavi.elonet_elokuva_1235865","images":["/Cover/Show?id=kavi.elonet_elokuva_1235865&index=0&size=large&source=Solr"],"urls":[{"url":"http://www.elonet.fi/fi/video/1652951_1235865","posterUrl":"http://www.elonet.fi/tenho/media/1652951_suoratoisto_esikatselu.jpg","videoSources":[{"src":"https://elo.salama.tv.funet.fi/vod/_definst_/mp4:fi/kava/elonet/2015/1237370_Mielihyva15sec_1.mp4/playlist.m3u8","type":"application/x-mpegURL","priority":1},{"src":"https://elo.salama.tv.funet.fi/vod/_definst_/mp4:fi/kava/elonet/2015/1237370_Mielihyva15sec_1.mp4/manifest.mpd","type":"application/dash+xml","priority":2}],"text":"elokuva","desc":"elokuva","source":"kavi","embed":"video","warnings":["age_rating_for_all_ages"]}],"recordPage":"/Record/kavi.elonet_elokuva_1235865","imageRights":{"copyright":"Luvanvarainen käyttö / ei tiedossa"},"buildings":[{"value":"0/KAVI/","translated":"Kansallinen audiovisuaalinen instituutti"}],"rawData":{"record_format":"forward","ctrlnum":["elonet_elokuva_1235865"],"title":"Mielihyvä 15 sek.","title_txtP":"Mielihyvä 15 sek.","title_alt":["Mielihyvä 15\"","Raisio Mielihyvä perunamuusi"],"title_full":"Mielihyvä 15 sek.","title_fullStr":"Mielihyvä 15 sek.","title_full_unstemmed":"Mielihyvä 15 sek.","title_short":"Mielihyvä 15 sek.","description":"Mainostetaan perunasosejauhetta.","topic":["elintarvikkeet"],"url":["http://www.elonet.fi/fi/elokuva/1235865","http://www.elonet.fi/fi/video/1652951_1235865"],"thumbnail":"http://www.elonet.fi/tenho/media/1652951_digikuva_suoratoisto_thumbnail.jpg","author_corporate":["Filmitalo Oy"],"author_corporate_role":["e10"],"geographic":["Suomi"],"genre":["mainos"],"format":[{"value":"0/Video/","translated":"Video"},{"value":"1/Video/Short/","translated":"Elokuva, lyhyt"}],"main_date":"1964-01-01T00:00:00Z","publication_daterange":"[1964-01-01 TO 1964-12-31]","search_daterange_mv":["[1964-01-01 TO 1964-12-31]"],"author_facet":["Filmitalo Oy"],"language":["fin"],"id":"kavi.elonet_elokuva_1235865","is_hierarchy_id":"kavi.elonet_elokuva_1235865","is_hierarchy_title":"Mielihyvä 15 sek.","first_indexed":"2019-12-19T23:00:01Z","last_indexed":"2021-04-30T06:34:30Z","publishDate":["1964"],"building":[{"value":"0/KAVI/","translated":"Kansallinen audiovisuaalinen instituutti"}],"institution":["KAVI"],"sector_str_mv":[{"value":"0/arc/","translated":"Arkisto"}],"topic_facet":["elintarvikkeet"],"online_boolean":1,"genre_facet":["mainos"],"online_str_mv":["kavi"],"free_online_str_mv":["kavi"],"source_str_mv":["kavi"],"geographic_facet":["Suomi"],"author2_id_str_mv":["kavi.elonet_henkilo_118589","kavi.elonet_henkilo_233898","kavi.elonet_henkilo_253213","kavi.elonet_yhtio_124696","kavi.elonet_yhtio_145697","kavi.elonet_yhtio_211551"],"author2_id_role_str_mv":["kavi.elonet_henkilo_118589###esiintyjä","kavi.elonet_henkilo_233898###esiintyjä","kavi.elonet_henkilo_253213###esiintyjä","kavi.elonet_yhtio_124696###tilaaja","kavi.elonet_yhtio_145697###fds","kavi.elonet_yhtio_211551###fmp"],"main_date_str":"1964","title_sort":"Mielihyvä 15 sek.","free_online_boolean":1,"online_urls_str_mv":["{\"url\":\"http:\\/\\/www.elonet.fi\\/fi\\/video\\/1652951_1235865\",\"text\":\"elokuva\",\"source\":\"kavi\"}"],"format_ext_str_mv":[{"value":"0/Image/","translated":"Kuva"},{"value":"0/Video/","translated":"Video"},{"value":"1/Image/Image/","translated":"Kuva"},{"value":"1/Video/Short/","translated":"Elokuva, lyhyt"}],"datasource_str_mv":["kavi"],"_version_":1704730706374033400}}