{"title":"Rovaniemi rakentaa","id":"kavi.elonet_elokuva_114370","images":["/Cover/Show?id=kavi.elonet_elokuva_114370&index=0&size=large&source=Solr"],"urls":[{"url":"http://www.elonet.fi/fi/video/462449_114370","posterUrl":"http://www.elonet.fi/tenho/media/462449_suoratoisto_esikatselu.jpg","videoSources":[{"src":"https://elo.salama.tv.funet.fi/vod/_definst_/mp4:fi/kava/elonet/2012/MV-187_RovaniemiRakentaa.mp4/playlist.m3u8","type":"application/x-mpegURL","priority":1},{"src":"https://elo.salama.tv.funet.fi/vod/_definst_/mp4:fi/kava/elonet/2012/MV-187_RovaniemiRakentaa.mp4/manifest.mpd","type":"application/dash+xml","priority":2}],"text":"elokuva","desc":"elokuva","source":"kavi","embed":"video","warnings":[]}],"recordPage":"/Record/kavi.elonet_elokuva_114370","imageRights":{"copyright":"Luvanvarainen käyttö / ei tiedossa"},"buildings":[{"value":"0/KAVI/","translated":"Kansallinen audiovisuaalinen instituutti"}],"rawData":{"record_format":"forward","ctrlnum":["elonet_elokuva_114370"],"title":"Rovaniemi rakentaa","title_txtP":"Rovaniemi rakentaa","title_alt":["Rovaniemi återuppbygger","Rovaniemi rises again","Rovaniemi rebuilds","Rebuilding Rovaniemi"],"title_full":"Rovaniemi rakentaa","title_fullStr":"Rovaniemi rakentaa","title_full_unstemmed":"Rovaniemi rakentaa","title_short":"Rovaniemi rakentaa","description":"Holger Harrivirran (1915-1986) lyhytelokuva kesältä 1945. Rovaniemi on rauniokasana. Lapin läänin hermokeskus tuhottiin niin perusteellisesti, että vain kauppalan reunoilla oli jäljellä satakunta rakennusta, nekin osin hävitettyinä. Suomen Lappi oli Euroopan täydellisimmin hävitettyä seutua. Romusta ei ole puutetta kesällä 1945, toki jalkapallo pyörii raunioiden keskelläkin. Ja Pohjanhovin viinikellari \"Hovinpohja\" toimii. Mutta ei<br />viini vaan lehmä, se on vähäväkisen elämän alku. Elämä herää väkevänä Pohjolassa! Tuhkastakin nousee uusi elämä! Maatalousministeriö-tekstillä varustettu lastattu kuorma-auto ajaa. Tienviittoja. Yleiskuvaa tuhotusta Rovaniemestä. Raunioita, etualalla mies kävelee lehmää taluttaen. Raunioita, savua, kellariaukko maassa. Mies nousee kellarista ämpäriä kantaen. Toinen kellariasumus, josta mies nousee. Pojat pelaavat jalkapalloa raunioiden keskellä. Auto ajaa pölyävällä tiellä. Uusia tontteja mitoitetaan uudisrakentamista varten. Raunioita räjäytetään. Näytetään rauniokasoja. Välähdys tuhoutuneesta elokuvateatterista, seinässä teksti Kino teatteri. Uudisrakentamiseen tarkoitettuja puhdistettuja tiilikasoja. Miehet moukaroivat  rauniokasoja. Melko tuhoutunut talo, jonka katolla savukemainos Klubi piristää. Hevonen vetää raskaasti lastattuja kärryjä. Mies puhdistaa tiiliä. Kuvia raunioista. Aidassa Miinat poistettu -kilpi. Kuvia tuhoutuneesta keskustasta, jossa sijainnut mm. lääninhallitus, suojeluskuntapiiri, Veitsiluoto ja muita Rovaniemen keskeisiä rakennuksia. Kyltti Huom. Räjähtämätön pommi. Tuhoutunut talo. Miehet lapiohommissa. Talon perustusta rakennetaan. Rakennustelineitä ja rakenteilla oleva katto. Kaksi miestä ja puhelinlankavyyhtejä. Nainen tamppaa mattoja. Raunioita. Mies menee ehjään toimistotaloon. Lähikuvia toimistokylteistä: ”Kemijoen uittoyhdistys” ja ”Kaarto r.y.”, toisaalla ”Lapin läänin kansanhuoltopiirin piiritoimisto”, [”O.Y. Pohjoismaiden Yhdyspankki”] sekä ”Veitsiluoto Osakeyhtiö”. Puutalo, josta tulee kaksi hoitajan asuihin pukeutunutta naista saavia kantaen. Kyltti puutalon seinässä: Mlk:n Kulkutautisairaala. Hoitajatar ja kätilö. Lähikuvat heistä erikseen. Apteekki, autohuoltamo, kauppa, kioski. Kirjettä lukeva poika. Sanomalehteä tutkiva mies. Lapin Kansan tuhoutunut kirjapaino. Palaneita painokoneita. Asuntoparakkeja. Lähikuvassa vanha mies kirvestöissä. Vanha talon piippu ja telineet. Miehet menossa saunaan vihdat kainaloissaan. Ilmoitus seinässä: Yllätysohjelma ja tanssia Järjestöjen parakissa sekä esiintyjien nimiä (Talikkalan Taitovoimistelijat, Pirkko Hurme, Aarno Walli, Anja Selenius, Olli Lehtinen, Mr. Bruno, Yrjö Irjanne). Näkymä entisen Pohjanhovin suuntaan. Raunioita, romua. Roskapönttö. Näkymää Pohjanhovin entiseltä alueelta. Ravintolaksi kunnostettu parakkirakennus. Ihmisiä. Miehiä istuskelemassa ravintolan edustalla ja seisoskelemassa kadulla. Karjaa avolavaisilla autoilla. Mies syö veitsellä lihaa.Karjaa avolavaisilla autoilla. Lossi. Matkustajia, karjaa, tavaroiden lastausta. Karjaa avolavaisilla autoilla. Lossin perämiehet työssään. Vettä, tuhottuja siltoja, Rovaniemen taloja. Siltatyömaa. Sukeltaja työssään. Mies kyntää peltoa. Rakennustelineiden ympäröimä talo, ihmisiä. Kuva pimenee. Teksti Finlandia Kuva.","topic":["jälleenrakentaminen","Suomi","Rovaniemi","tuhot","jatkosota","Lapin sota","Lappi","rauniot","rauhanaika","sodanjälkeinen aika"],"url":["http://www.elonet.fi/fi/elokuva/114370","http://www.elonet.fi/fi/video/462449_114370"],"thumbnail":"http://www.elonet.fi/tenho/media/462449_digikuva_suoratoisto_thumbnail.jpg","author":["Holger Harrivirta"],"author_role":["d02"],"author_sort":"Holger Harrivirta","author2":["Holger Harrivirta","Kalevi Lavola"],"author2_role":["cng","flm"],"author_corporate":["Finlandia Kuva Oy"],"author_corporate_role":["e10"],"geographic":["Suomi"],"genre":["ajankohtaisdokumentti","dokumentti"],"format":[{"value":"0/Video/","translated":"Video"},{"value":"1/Video/Short/","translated":"Elokuva, lyhyt"}],"main_date":"1945-01-01T00:00:00Z","publication_daterange":"[1945-01-01 TO 1945-12-31]","search_daterange_mv":["[1945-01-01 TO 1945-12-31]"],"author_facet":["Holger Harrivirta","Kalevi Lavola","Finlandia Kuva Oy"],"language":["fin"],"id":"kavi.elonet_elokuva_114370","is_hierarchy_id":"kavi.elonet_elokuva_114370","is_hierarchy_title":"Rovaniemi rakentaa","first_indexed":"2017-04-11T11:57:00Z","last_indexed":"2021-04-30T06:33:20Z","publishDate":["1945"],"building":[{"value":"0/KAVI/","translated":"Kansallinen audiovisuaalinen instituutti"}],"institution":["KAVI"],"sector_str_mv":[{"value":"0/arc/","translated":"Arkisto"}],"topic_facet":["Lapin sota","Lappi","Rovaniemi","Suomi","jatkosota","jälleenrakentaminen","rauhanaika","rauniot","sodanjälkeinen aika","tuhot"],"online_boolean":1,"genre_facet":["ajankohtaisdokumentti","dokumentti"],"online_str_mv":["kavi"],"free_online_str_mv":["kavi"],"source_str_mv":["kavi"],"work_keys_str_mv":["AT harrivirtaholger rovaniemirakentaa"],"geographic_facet":["Suomi"],"author2_id_str_mv":["kavi.elonet_henkilo_107607","kavi.elonet_henkilo_114372","kavi.elonet_henkilo_712713","kavi.elonet_henkilo_712776","kavi.elonet_yhtio_1271977"],"author2_id_role_str_mv":["kavi.elonet_henkilo_107607###flm","kavi.elonet_henkilo_114372###spk,","kavi.elonet_henkilo_712713###cng","kavi.elonet_henkilo_712713###drt","kavi.elonet_henkilo_712776###selostusteksti","kavi.elonet_yhtio_1271977###fmp"],"main_date_str":"1945","title_sort":"Rovaniemi rakentaa","free_online_boolean":1,"online_urls_str_mv":["{\"url\":\"http:\\/\\/www.elonet.fi\\/fi\\/video\\/462449_114370\",\"text\":\"elokuva\",\"source\":\"kavi\"}"],"format_ext_str_mv":[{"value":"0/Image/","translated":"Kuva"},{"value":"0/Video/","translated":"Video"},{"value":"1/Image/Image/","translated":"Kuva"},{"value":"1/Video/Short/","translated":"Elokuva, lyhyt"}],"datasource_str_mv":["kavi"],"_version_":1704525786987364400}}